WIPClient/WIPClient.py
WIPClient/WIPClientAbstractModel.py
WIPClient/WIPClient_advance.py
WIPClient/WIPClient_advance_original.py
WIPClient/WIPDevice.py
WIPClient/__init__.py
WIPClient/interface/HTTPSocketManager.py
WIPClient/interface/SocketManager.py
WIPClient/interface/SocketManagerV2.py
WIPClient/interface/WebSocketManager.py
WIPClient/interface/__init__.py
WIPClient/protocol/__init__.py
WIPClient/protocol/advanced/ConstantVar.py
WIPClient/protocol/advanced/JsonDataProtocol.py
WIPClient/protocol/advanced/ModelJsonData.py
WIPClient/protocol/advanced/__init__.py
WIPClient/protocol/advanced/aes256.py
WIPClient/protocol/advanced/commonFunction.py
WIPDevice/WIPClient.py
WIPDevice/WIPClientAbstractModel.py
WIPDevice/WIPClient_advance.py
WIPDevice/WIPDevice.py
WIPDevice/__init__.py
WIPDevice/interface/HTTPSocketManager.py
WIPDevice/interface/SocketManager.py
WIPDevice/interface/SocketManagerV2.py
WIPDevice/interface/WebSocketManager.py
WIPDevice/interface/__init__.py
WIPDevice/protocol/__init__.py
WIPDevice/protocol/advanced/ConstantVar.py
WIPDevice/protocol/advanced/JsonDataProtocol.py
WIPDevice/protocol/advanced/ModelJsonData.py
WIPDevice/protocol/advanced/__init__.py
WIPDevice/protocol/advanced/aes256.py
WIPDevice/protocol/advanced/commonFunction.py
wipdevice-0.1.3.dist-info/METADATA
wipdevice-0.1.3.dist-info/WHEEL
wipdevice-0.1.3.dist-info/top_level.txt
wipdevice-0.1.3.dist-info/RECORD
